exceldrive2py/__init__.py
exceldrive2py-0.0.1.dist-info/LICENSE.txt
exceldrive2py-0.0.1.dist-info/METADATA
exceldrive2py-0.0.1.dist-info/WHEEL
exceldrive2py-0.0.1.dist-info/top_level.txt
exceldrive2py-0.0.1.dist-info/RECORD
