Metadata-Version: 2.1
Name: exceldrive2py
Version: 0.0.1
Summary: Read en excel file throgh google drive and plot it
Home-page: https://github.com/afsarahmad786/Read-Excel
Author: Mohammad Afsar
Author-email: mohammadafsar415@gmail.com
License: UNKNOWN
Platform: UNKNOWN
Classifier: Programming Language :: Python :: 3
Classifier: License :: OSI Approved :: MIT License
Classifier: Operating System :: OS Independent
